plytix_pim_client/__init__.py
plytix_pim_client/client.py
plytix_pim_client/config.py
plytix_pim_client/constants.py
plytix_pim_client/exceptions.py
plytix_pim_client/logger.py
plytix_pim_client/mixins.py
plytix_pim_client/version.py
plytix_pim_client/api/__init__.py
plytix_pim_client/api/base.py
plytix_pim_client/api/filters.py
plytix_pim_client/api/assets/__init__.py
plytix_pim_client/api/assets/search.py
plytix_pim_client/api/assets/asset/__init__.py
plytix_pim_client/api/assets/asset/create.py
plytix_pim_client/api/assets/asset/delete.py
plytix_pim_client/api/assets/asset/get.py
plytix_pim_client/api/assets/asset/replace.py
plytix_pim_client/api/assets/asset/update.py
plytix_pim_client/api/assets/categories/__init__.py
plytix_pim_client/api/assets/categories/search.py
plytix_pim_client/api/assets/categories/category/__init__.py
plytix_pim_client/api/assets/categories/category/create.py
plytix_pim_client/api/assets/categories/category/delete.py
plytix_pim_client/api/assets/categories/category/update.py
plytix_pim_client/api/common/__init__.py
plytix_pim_client/api/common/create.py
plytix_pim_client/api/common/delete.py
plytix_pim_client/api/common/get.py
plytix_pim_client/api/common/search.py
plytix_pim_client/api/common/update.py
plytix_pim_client/api/products/__init__.py
plytix_pim_client/api/products/search.py
plytix_pim_client/api/products/attributes/__init__.py
plytix_pim_client/api/products/attributes/search.py
plytix_pim_client/api/products/attributes/attribute/__init__.py
plytix_pim_client/api/products/attributes/attribute/create.py
plytix_pim_client/api/products/attributes/attribute/delete.py
plytix_pim_client/api/products/attributes/attribute/get.py
plytix_pim_client/api/products/attributes/attribute/update.py
plytix_pim_client/api/products/attributes/groups/__init__.py
plytix_pim_client/api/products/attributes/groups/search.py
plytix_pim_client/api/products/attributes/groups/group/__init__.py
plytix_pim_client-1.3.0.dist-info/licenses/LICENSE
plytix_pim_client-1.3.0.dist-info/METADATA
plytix_pim_client-1.3.0.dist-info/WHEEL
plytix_pim_client-1.3.0.dist-info/top_level.txt
plytix_pim_client-1.3.0.dist-info/RECORD
