Metadata-Version: 2.4
Name: plytix-pim-client
Version: 1.3.0
Summary: An HTTP client in Python for Plytix PIM API.
Author-email: Arturo Parra <arturoteleco95@proton.me>
Project-URL: Homepage, https://github.com/TheTelematic/plytix-pim-client
Project-URL: Issues, https://github.com/TheTelematic/plytix-pim-client/issues
Classifier: Programming Language :: Python :: 3
Classifier: License :: OSI Approved :: MIT License
Classifier: Operating System :: OS Independent
Requires-Python: >=3.11
License-File: LICENSE
Requires-Dist: httpx~=0.27.2
Requires-Dist: aiofiles~=24.1.0
Dynamic: license-file
